hypex/__init__.py
hypex/__version__.py
hypex/aa.py
hypex/ab.py
hypex/analyzers/__init__.py
hypex/analyzers/aa.py
hypex/analyzers/ab.py
hypex/analyzers/matching.py
hypex/comparators/__init__.py
hypex/comparators/abstract.py
hypex/comparators/comparators.py
hypex/comparators/distances.py
hypex/comparators/hypothesis_testing.py
hypex/comparators/power_testing.py
hypex/dataset/__init__.py
hypex/dataset/abstract.py
hypex/dataset/backends/__init__.py
hypex/dataset/backends/abstract.py
hypex/dataset/backends/pandas_backend.py
hypex/dataset/dataset.py
hypex/dataset/roles.py
hypex/encoders/__init__.py
hypex/encoders/abstract.py
hypex/encoders/encoders.py
hypex/executor/__init__.py
hypex/executor/calculators.py
hypex/executor/executor.py
hypex/experiments/__init__.py
hypex/experiments/base.py
hypex/experiments/base_complex.py
hypex/extensions/__init__.py
hypex/extensions/abstract.py
hypex/extensions/cupac.py
hypex/extensions/encoders.py
hypex/extensions/faiss.py
hypex/extensions/scipy_linalg.py
hypex/extensions/scipy_stats.py
hypex/extensions/statsmodels.py
hypex/factory/__init__.py
hypex/factory/base.py
hypex/forks/__init__.py
hypex/forks/aa.py
hypex/homogeneity.py
hypex/hypotheses/__init__.py
hypex/hypotheses/hypothesis.py
hypex/hypotheses/schemes/scheme.json
hypex/matching.py
hypex/ml/__init__.py
hypex/ml/cupac.py
hypex/ml/faiss.py
hypex/operators/__init__.py
hypex/operators/abstract.py
hypex/operators/operators.py
hypex/preprocessing.py
hypex/reporters/__init__.py
hypex/reporters/aa.py
hypex/reporters/ab.py
hypex/reporters/abstract.py
hypex/reporters/homo.py
hypex/reporters/matching.py
hypex/splitters/__init__.py
hypex/splitters/aa.py
hypex/transformers/__init__.py
hypex/transformers/abstract.py
hypex/transformers/category_agg.py
hypex/transformers/cuped.py
hypex/transformers/filters.py
hypex/transformers/na_filler.py
hypex/transformers/shuffle.py
hypex/transformers/type_caster.py
hypex/ui/__init__.py
hypex/ui/aa.py
hypex/ui/ab.py
hypex/ui/base.py
hypex/ui/homo.py
hypex-1.0.3.dist-info/METADATA
hypex-1.0.3.dist-info/WHEEL
hypex-1.0.3.dist-info/licenses/LICENSE
hypex-1.0.3.dist-info/RECORD
