Metadata-Version: 2.4
Name: HypEx
Version: 1.0.3
Summary: Fast and customizable framework for Causal Inference
License: Apache-2.0
License-File: LICENSE
Author: Dmitry Tikhomirov
Author-email: dimasta00@gmail.com
Requires-Python: >=3.8,<3.14
Classifier: Development Status :: 4 - Beta
Classifier: Environment :: Console
Classifier: Intended Audience :: Science/Research
Classifier: License :: OSI Approved :: Apache Software License
Classifier: Natural Language :: English
Classifier: Operating System :: OS Independent
Classifier: Programming Language :: Python :: 3
Classifier: Programming Language :: Python :: 3.8
Classifier: Programming Language :: Python :: 3.9
Classifier: Programming Language :: Python :: 3.10
Classifier: Programming Language :: Python :: 3.11
Classifier: Programming Language :: Python :: 3.12
Classifier: Programming Language :: Python :: 3.13
Classifier: Programming Language :: Python :: 3 :: Only
Classifier: Topic :: Scientific/Engineering :: Artificial Intelligence
Classifier: Topic :: Scientific/Engineering :: Mathematics
Classifier: Typing :: Typed
Provides-Extra: all
Provides-Extra: cat
Provides-Extra: lgbm
Requires-Dist: faiss-cpu (>=1.6.0,<=1.8.0) ; python_version < "3.9"
Requires-Dist: faiss-cpu (>=1.9.0,<=1.14.0) ; python_version >= "3.9"
Requires-Dist: matplotlib (>=3.0.0,<=3.7.3) ; python_version < "3.9"
Requires-Dist: matplotlib (>=3.0.0,<=3.9.0) ; python_version >= "3.9" and python_version < "3.13"
Requires-Dist: matplotlib (>=3.10.0,<=3.11.0) ; python_version >= "3.13"
Requires-Dist: numpy (>=1.17.0,<=1.24.4) ; python_version < "3.9"
Requires-Dist: numpy (>=1.17.0,<=1.26.4) ; python_version >= "3.9"
Requires-Dist: pandas (>=1.3.5,<=2.0.3) ; python_version < "3.9"
Requires-Dist: pandas (>=1.3.5,<=2.2.3) ; python_version >= "3.9"
Requires-Dist: scikit-learn
Requires-Dist: scipy (>=1.14.1,<=1.16.0) ; python_version >= "3.13"
Requires-Dist: scipy (>=1.5.0,<=1.10.1) ; python_version < "3.9"
Requires-Dist: scipy (>=1.5.0,<=1.13.1) ; python_version >= "3.9" and python_version < "3.13"
Requires-Dist: seaborn (<=0.13.2)
Requires-Dist: statsmodels (<=0.14.2)
Requires-Dist: tqdm
Project-URL: Repository, https://github.com/sb-ai-lab/HypEx
